multimil/__init__.py
multimil/dataloaders/__init__.py
multimil/dataloaders/_ann_dataloader.py
multimil/dataloaders/_data_splitting.py
multimil/model/__init__.py
multimil/model/_mil.py
multimil/module/__init__.py
multimil/module/_mil_torch.py
multimil/nn/__init__.py
multimil/nn/_base_components.py
multimil/utils/__init__.py
multimil/utils/_utils.py
multimil-0.3.2.dist-info/METADATA
multimil-0.3.2.dist-info/WHEEL
multimil-0.3.2.dist-info/licenses/LICENSE
multimil-0.3.2.dist-info/RECORD
