Metadata-Version: 2.4
Name: multimil
Version: 0.3.2
Summary: Multimodal weakly supervised learning to identify disease-specific changes in single-cell atlases
Project-URL: Documentation, https://multimil.readthedocs.io/
Project-URL: Source, https://github.com/theislab/multimil
Project-URL: Home-page, https://github.com/theislab/multimil
Author: Anastasia Litinetskaya
Maintainer-email: Anastasia Litinetskaya <alitinet@gmail.com>
License: BSD 3-Clause License
License-File: LICENSE
Requires-Python: >=3.10
Requires-Dist: anndata<0.11
Requires-Dist: jax<0.6
Requires-Dist: matplotlib
Requires-Dist: numpy<2.0
Requires-Dist: requests
Requires-Dist: scanpy
Requires-Dist: scvi-tools<1.0.0
Requires-Dist: session-info
Provides-Extra: dev
Requires-Dist: pre-commit; extra == 'dev'
Requires-Dist: twine>=4.0.2; extra == 'dev'
Provides-Extra: doc
Requires-Dist: docutils!=0.18.*,!=0.19.*,>=0.8; extra == 'doc'
Requires-Dist: ipykernel; extra == 'doc'
Requires-Dist: ipython; extra == 'doc'
Requires-Dist: myst-nb>=1.1.0; extra == 'doc'
Requires-Dist: pandas; extra == 'doc'
Requires-Dist: setuptools; extra == 'doc'
Requires-Dist: sphinx-autodoc-typehints; extra == 'doc'
Requires-Dist: sphinx-book-theme>=1.0.0; extra == 'doc'
Requires-Dist: sphinx-copybutton; extra == 'doc'
Requires-Dist: sphinx>=4; extra == 'doc'
Requires-Dist: sphinxcontrib-bibtex>=1.0.0; extra == 'doc'
Requires-Dist: sphinxext-opengraph; extra == 'doc'
Provides-Extra: test
Requires-Dist: coverage; extra == 'test'
Requires-Dist: pytest; extra == 'test'
Provides-Extra: tutorials
Requires-Dist: gdown; extra == 'tutorials'
Requires-Dist: igraph; extra == 'tutorials'
Requires-Dist: ipywidgets; extra == 'tutorials'
Requires-Dist: jupyterlab; extra == 'tutorials'
Requires-Dist: leidenalg; extra == 'tutorials'
